librelingo_types/__init__.py
librelingo_types/data_types.py
librelingo_types-3.3.0.dist-info/WHEEL
librelingo_types-3.3.0.dist-info/METADATA
librelingo_types-3.3.0.dist-info/RECORD
