Metadata-Version: 2.1
Name: librelingo-types
Version: 3.3.0
Summary: Data types to be used in Python packages for LibreLingo
License: GPLv3
Author: Dániel Kántor
Author-email: git@daniel-kantor.com
Requires-Python: >=3.8,<4.0
Classifier: License :: Other/Proprietary License
Classifier: Programming Language :: Python :: 3
Classifier: Programming Language :: Python :: 3.10
Classifier: Programming Language :: Python :: 3.8
Classifier: Programming Language :: Python :: 3.9
